heimdall_python_sdk/__init__.py
heimdall_python_sdk/core.py
heimdall_python_sdk/django_impl.py
heimdall_python_sdk/fastapi_impl.py
heimdall_python_sdk/flask_impl.py
heimdall_python_sdk-0.1.3.dist-info/licenses/LICENSE
heimdall_python_sdk-0.1.3.dist-info/METADATA
heimdall_python_sdk-0.1.3.dist-info/WHEEL
heimdall_python_sdk-0.1.3.dist-info/top_level.txt
heimdall_python_sdk-0.1.3.dist-info/RECORD
