Metadata-Version: 2.4
Name: heimdall_python_sdk
Version: 0.1.3
Summary: A cross-framework Python SDK to register a /__ping__ endpoint for Flask, Django, and FastAPI apps.
Author-email: Shivdutt Bhadakwad <shivdutt059@example.com>
License: MIT
Project-URL: Homepage, https://github.com/shivdutt-B/heimdall-python-sdk
Project-URL: Issues, https://github.com/shivdutt-B/heimdall-python-sdk/issues
Keywords: ping,warmup,server,monitoring,flask,django,fastapi,keepalive
Classifier: Programming Language :: Python :: 3
Classifier: License :: OSI Approved :: MIT License
Classifier: Operating System :: OS Independent
Requires-Python: >=3.7
License-File: LICENSE
Requires-Dist: flask>=2.0.0
Requires-Dist: fastapi>=0.70.0
Requires-Dist: django>=3.2
Requires-Dist: uvicorn
Dynamic: license-file
